django_monkey_patches/__init__.py
django_monkey_patches/dev_side_code__django__orm__prefetch_1.py
django_monkey_patches/django__base_cache__make_cache_key.py
django_monkey_patches/django__orm__prefetch.py
django_monkey_patches/django__orm__prefetch_without_useless_order_by.py
django_monkey_patches/django__query_set.py
django_monkey_patches/django__query_set__get.py
django_monkey_patches/django__query_set__get_or_create.py
django_monkey_patches/django__query_wrapper.py
django_monkey_patches/django__test_case__tear_down.py
django_monkey_patches/django_rest_framework__field__get_request.py
django_monkey_patches/django_rest_framework__list_serializer__to_representation.py
django_monkey_patches-4.0.1.dist-info/METADATA
django_monkey_patches-4.0.1.dist-info/WHEEL
django_monkey_patches-4.0.1.dist-info/licenses/COPYING
django_monkey_patches-4.0.1.dist-info/licenses/COPYING.LESSER
django_monkey_patches-4.0.1.dist-info/RECORD
