Metadata-Version: 2.3
Name: django-monkey-patches
Version: 4.0.1
Summary: Add monkey-patches to correct and enhance your favorite framework
Project-URL: Homepage, https://github.com/LLyaudet/django-monkey-patches
Project-URL: Bug Tracker, https://github.com/LLyaudet/django-monkey-patches/issues
Author-email: Laurent Lyaudet <laurent.lyaudet@gmail.com>
Maintainer-email: Laurent Lyaudet <laurent.lyaudet@gmail.com>
License:                    GNU LESSER GENERAL PUBLIC LICENSE
License-File: COPYING
License-File: COPYING.LESSER
Keywords: Django,monkey-patch
Classifier: Development Status :: 5 - Production/Stable
Classifier: Framework :: Django
Classifier: Intended Audience :: Developers
Classifier: License :: OSI Approved :: GNU Lesser General Public License v3 or later (LGPLv3+)
Classifier: Operating System :: OS Independent
Classifier: Programming Language :: Python
Classifier: Programming Language :: Python :: 3
Classifier: Topic :: Software Development :: Libraries :: Application Frameworks
Classifier: Topic :: Software Development :: Libraries :: Python Modules
Requires-Python: >=3.0
Provides-Extra: dev
Requires-Dist: black; extra == 'dev'
Requires-Dist: isort; extra == 'dev'
Requires-Dist: pylint; extra == 'dev'
